claude_smart_fork/__init__.py
claude_smart_fork/__main__.py
claude_smart_fork/cli.py
claude_smart_fork/config.py
claude_smart_fork/indexer.py
claude_smart_fork/parser.py
claude_smart_fork/search.py
claude_smart_fork/backends/__init__.py
claude_smart_fork/backends/base.py
claude_smart_fork/backends/chromadb.py
claude_smart_fork/backends/sqlite.py
claude_smart_fork/embeddings/__init__.py
claude_smart_fork/embeddings/api.py
claude_smart_fork/embeddings/base.py
claude_smart_fork/embeddings/local.py
claude_smart_fork/hooks/__init__.py
claude_smart_fork/hooks/prompt_submit.py
claude_smart_fork/hooks/session_end.py
claude_smart_fork/summarizers/__init__.py
claude_smart_fork/summarizers/base.py
claude_smart_fork/summarizers/claude.py
claude_smart_fork/summarizers/ollama.py
claude_smart_fork/summarizers/simple.py
claude_smart_fork-0.1.0.dist-info/METADATA
claude_smart_fork-0.1.0.dist-info/WHEEL
claude_smart_fork-0.1.0.dist-info/entry_points.txt
claude_smart_fork-0.1.0.dist-info/licenses/LICENSE
claude_smart_fork-0.1.0.dist-info/RECORD
