Metadata-Version: 2.4
Name: claude-smart-fork
Version: 0.1.0
Summary: Semantic search across Claude Code sessions to find the best context for new tasks
Project-URL: Homepage, https://github.com/a-bekheet/claude-smart-fork
Project-URL: Documentation, https://github.com/a-bekheet/claude-smart-fork#readme
Project-URL: Repository, https://github.com/a-bekheet/claude-smart-fork
Project-URL: Issues, https://github.com/a-bekheet/claude-smart-fork/issues
Project-URL: Changelog, https://github.com/a-bekheet/claude-smart-fork/blob/main/CHANGELOG.md
Author-email: a-bekheet <alibekheet@outlook.com>
License-Expression: MIT
License-File: LICENSE
Keywords: ai,claude,claude-code,cli,llm,search,semantic-search,session,vector-database
Classifier: Development Status :: 3 - Alpha
Classifier: Environment :: Console
Classifier: Intended Audience :: Developers
Classifier: License :: OSI Approved :: MIT License
Classifier: Operating System :: OS Independent
Classifier: Programming Language :: Python :: 3
Classifier: Programming Language :: Python :: 3.10
Classifier: Programming Language :: Python :: 3.11
Classifier: Programming Language :: Python :: 3.12
Classifier: Programming Language :: Python :: 3.13
Classifier: Topic :: Software Development :: Libraries :: Python Modules
Classifier: Topic :: Utilities
Classifier: Typing :: Typed
Requires-Python: >=3.10
Requires-Dist: pydantic-settings>=2.0.0
Requires-Dist: pydantic>=2.0.0
Requires-Dist: rich>=13.0.0
Requires-Dist: typer>=0.9.0
Provides-Extra: all
Requires-Dist: anthropic>=0.18.0; extra == 'all'
Requires-Dist: chromadb>=0.4.0; extra == 'all'
Requires-Dist: ollama>=0.1.0; extra == 'all'
Requires-Dist: sentence-transformers>=2.2.0; extra == 'all'
Requires-Dist: torch>=2.0.0; extra == 'all'
Provides-Extra: chromadb
Requires-Dist: chromadb>=0.4.0; extra == 'chromadb'
Provides-Extra: claude
Requires-Dist: anthropic>=0.18.0; extra == 'claude'
Provides-Extra: dev
Requires-Dist: mypy>=1.0.0; extra == 'dev'
Requires-Dist: pre-commit>=3.0.0; extra == 'dev'
Requires-Dist: pytest-asyncio>=0.21.0; extra == 'dev'
Requires-Dist: pytest-cov>=4.0.0; extra == 'dev'
Requires-Dist: pytest>=7.0.0; extra == 'dev'
Requires-Dist: ruff>=0.1.0; extra == 'dev'
Provides-Extra: embeddings
Requires-Dist: sentence-transformers>=2.2.0; extra == 'embeddings'
Requires-Dist: torch>=2.0.0; extra == 'embeddings'
Provides-Extra: ollama
Requires-Dist: ollama>=0.1.0; extra == 'ollama'
